config/__init__.py
config/get_config.py
datahelper/api/__init__.py
datahelper/api/dataplatform_api_helper.py
datahelper/dynamodb/__init__.py
datahelper/dynamodb/dynamodb_data_helper.py
datahelper/dynamodb/learningdb_dev_data_helper.py
datahelper/mongodb/__init__.py
datahelper/mongodb/dataplatform_data_helper.py
datahelper/mongodb/mongodb_data_helper.py
datahelper/mongodb/data_platform/__init__.py
datahelper/mongodb/data_platform/find.py
datahelper/mssql/__init__.py
datahelper/mssql/goserver_production_data_helper.py
datahelper/mssql/mssql_data_helper.py
datahelper/mssql/go_server_production/__init__.py
datahelper/mssql/go_server_production/select.py
datahelper/s3/__init__.py
datahelper/s3/mllearningdb_data_helper.py
datahelper/s3/s3_data_helper.py
datahelper/s3/ml_learningdb/__init__.py
datahelper/s3/ml_learningdb/s3_path_helper.py
mlcore/__init__.py
mlcore/__version__.py
mlcore/config/__init__.py
mlcore/config/get_config.py
mlcore/datahelper/__init__.py
mlcore/datahelper/api/__init__.py
mlcore/datahelper/api/dataplatform_api_helper.py
mlcore/datahelper/api/keycloak_sdk.py
mlcore/datahelper/api/mongodb_api_helper.py
mlcore/datahelper/athena/__init__.py
mlcore/datahelper/athena/athena_helper.py
mlcore/datahelper/athena/mllearningdb_helper.py
mlcore/datahelper/athena/mllearningdb/__init__.py
mlcore/datahelper/athena/mllearningdb/create.py
mlcore/datahelper/athena/mllearningdb/update.py
mlcore/datahelper/dynamodb/__init__.py
mlcore/datahelper/dynamodb/dynamodb_data_helper.py
mlcore/datahelper/dynamodb/learningdb_dev_data_helper.py
mlcore/datahelper/mongodb/__init__.py
mlcore/datahelper/mongodb/dataplatform_data_helper.py
mlcore/datahelper/mongodb/mongodb_data_helper.py
mlcore/datahelper/mongodb/dataplatform/__init__.py
mlcore/datahelper/mongodb/dataplatform/find.py
mlcore/datahelper/mssql/__init__.py
mlcore/datahelper/mssql/goserver_production_data_helper.py
mlcore/datahelper/mssql/mssql_data_helper.py
mlcore/datahelper/mssql/go_server_production/__init__.py
go_ml_core-0.1.3.dev3.dist-info/METADATA
go_ml_core-0.1.3.dev3.dist-info/WHEEL
go_ml_core-0.1.3.dev3.dist-info/top_level.txt
go_ml_core-0.1.3.dev3.dist-info/RECORD
