Metadata-Version: 2.1
Name: go-ml-core
Version: 0.1.3.dev3
Summary: machine learning core library
Home-page: http://10.0.1.31/ML/ml-storage/ml-etl/
Author: henrychi
Author-email: shyuusaku@gmail.com
License: Gogoro Inc.
Keywords: machine learning
Platform: UNKNOWN
Classifier: Development Status :: 3 - Alpha
Classifier: Intended Audience :: Developers
Classifier: Topic :: Software Development :: Build Tools
Classifier: License :: OSI Approved :: MIT License
Classifier: Programming Language :: Python :: 3.4
Classifier: Programming Language :: Python :: 3.5
Classifier: Programming Language :: Python :: 3.6
Classifier: Programming Language :: Python :: 3.7
Requires-Dist: boto3 (>=1.9.57)
Requires-Dist: oss2 (>=2.9.1)
Requires-Dist: pymongo (>=3.7.2)
Requires-Dist: PyYAML (>=3.13)
Requires-Dist: requests (>=2.20.1)
